{"1970042": "Jessica Pegula", "1970027": "Hubert Hurkacz", "1969997": "Cori Gauff", "1969996": "Sara Sorribes Tormo", "1970024": "John Isner", "1969969": "Casper Ruud", "1970018": "Roberto Bautista-Agut", "1969995": "Aryna Sabalenka", "1970119": "Aryna Sabalenka", "1970120": "Stefanos Tsitsipas", "1970123": "Jessica Pegula", "1970124": "John Isner", "1970248": "Katerina Siniakova", "1970079": "Marco Cecchinato", "1970121": "Hugo Dellien", "1970277": "Anastasia Pavlyuchenkova", "1970265": "Angelique Kerber", "1970274": "Karolina Muchova", "1970295": "Sebastian Korda", "1970289": "Frances Tiafoe", "1970287": "Cameron Norrie", "1970281": "Hubert Hurkacz", "1970285": "Filip Krajinovic", "1970284": "Gael Monfils", "1970279": "Brandon Nakashima", "1970269": "Anett Kontaveit", "1970267": "Ekaterina Alexandrova", "1970271": "Elise Mertens", "1970270": "Simona Halep", "1970679": "Camila Giorgi", "1970681": "Daniil Medvedev", "1970264": "Caty McNally", "1970282": "Jan-Lennard Struff", "1970998": "Shuai Zhang", "1970999": "Annie Fernandez Leylah", "1971004": "Karen Khachanov", "1971048": "Sara Errani", "1971044": "Oceane Dodin", "1971039": "Anastasia Potapova", "1971043": "Zarina Diyas", "1971002": "Veronika Kudermetova", "1971001": "Viktoria Azarenka", "1971012": "Camila Giorgi", "1970280": "Grigor Dimitrov", "1970996": "Su-Wei Hsieh", "1970276": "Belinda Bencic", "1971008": "Cristian Garin", "1971007": "Corentin Moutet", "1971009": "Lorenzo Sonego", "1971006": "Marcos Giron", "1971010": "Benoit Paire", "1971440": "Fabio Fognini", "1971037": "Alison Van Uytvanck", "1971038": "Clara Burel", "1971040": "Nuria Parrizas-Diaz", "1971000": "Caroline Garcia", "1971504": "Ashleigh Barty", "1971047": "Hailey Baptiste", "1970272": "Elena Rybakina", "1971535": "Storm Sanders", "1971533": "Harriet Dart", "1971527": "Jule Niemeier", "1971526": "Rebecca Peterson", "1971536": "Ana Konjuh", "1971503": "Matteo Berrettini", "1970283": "Aslan Karatsev", "1971505": "Alexander Zverev", "1971508": "Karen Khachanov", "1971485": "Pablo Carreno-Busta", "1971482": "Anna Kalinskaya", "1971532": "Jennifer Brady", "1971506": "Aryna Sabalenka", "1971507": "Karolina Pliskova", "1971531": "Elina Svitolina", "1971774": "Belinda Bencic", "1971683": "Belen Teichmann Jil", "1971773": "Viktoria Azarenka", "1971763": "Petra Kvitova", "1971758": "Cori Gauff", "1971759": "Elise Mertens", "1971761": "Emma Raducanu", "1971745": "Alexander Bublik", "1971746": "Andy Murray", "1971742": "Vanessa Andreescu Bianca", "1971762": "Oceane Dodin", "1971756": "Vitalia Diatchenko", "1971688": "Clara Tauson", "1971743": "Sara Errani", "1971779": "Garbine Muguruza", "1971770": "Simona Halep", "1971771": "Ons Jabeur", "1971744": "Varvara Gracheva", "1971776": "Barbora Krejcikova", "1971768": "Casper Ruud", "1971764": "John Isner", "1971767": "Gael Monfils", "1971777": "Tommy Paul", "1971775": "Diego Schwartzman", "1971509": "Daniil Medvedev", "1971757": "Andrey Rublev", "1971678": "Sebastian Korda"}